gdolib/IG.py
gdolib/__init__.py
gdolib/check_email.py
gdolib/gdo_drow.py
gdolib/gdo_order.py
gdolib/info_face.py
gdolib/info_tiktok.py
gdolib/login.py
gdolib/fake/Fake_User.py
gdolib/fake/__init__.py
gdolib-0.2.4.dist-info/METADATA
gdolib-0.2.4.dist-info/WHEEL
gdolib-0.2.4.dist-info/top_level.txt
gdolib-0.2.4.dist-info/RECORD
