Metadata-Version: 2.1
Name: gdolib
Version: 0.2.4
Summary: • Script Very Nice To Helping Programmer .
Home-page: 
Author: GDO Tools
Author-email: GDOTools@gmail.com
Project-URL: Bug Tracker, https://github.com/pypa/sampleproject/issues
Classifier: Programming Language :: Python :: 3
Classifier: License :: OSI Approved :: MIT License
Classifier: Operating System :: OS Independent
Requires-Python: >=3.9
